octodns_ddns/__init__.py
octodns_ddns-0.2.1.dist-info/METADATA
octodns_ddns-0.2.1.dist-info/WHEEL
octodns_ddns-0.2.1.dist-info/top_level.txt
octodns_ddns-0.2.1.dist-info/RECORD
