Metadata-Version: 2.1
Name: octodns-ddns
Version: 0.2.1
Summary: octoDNS DDNS
Home-page: https://github.com/octodns/octodns-ddns
Author: Ross McFarland
Author-email: rwmcfa1@gmail.com
License: MIT
Platform: UNKNOWN
Requires-Python: >=3.6
Requires-Dist: octodns (>=0.9.14)
Requires-Dist: requests (>=2.27.0)
Provides-Extra: dev
Requires-Dist: pytest ; extra == 'dev'
Requires-Dist: pytest-network ; extra == 'dev'
Requires-Dist: build (>=0.7.0) ; extra == 'dev'
Requires-Dist: pycodestyle (>=2.6.0) ; extra == 'dev'
Requires-Dist: pyflakes (>=2.2.0) ; extra == 'dev'
Requires-Dist: readme-renderer[md] (>=26.0) ; extra == 'dev'
Requires-Dist: twine (>=3.4.2) ; extra == 'dev'
